<annotations><filename>00000129.JPEG</filename><folder>images</folder><size><width>1600</width><height>900</height><depth>3</depth></size><object><name>car</name><pose>Unspecified</pose><truncated>0</truncated><difficult>0</difficult><bndbox><xmin>0.9999999999999716</xmin><ymin>449.0</ymin><xmax>409.0</xmax><ymax>663.0</ymax></bndbox></object><object><name>car</name><pose>Unspecified</pose><truncated>0</truncated><difficult>0</difficult><bndbox><xmin>312.0</xmin><ymin>487.0</ymin><xmax>742.0</xmax><ymax>656.0</ymax></bndbox></object><object><name>car</name><pose>Unspecified</pose><truncated>0</truncated><difficult>0</difficult><bndbox><xmin>632.0000000000001</xmin><ymin>481.0</ymin><xmax>1026.0</xmax><ymax>644.0</ymax></bndbox></object><object><name>car</name><pose>Unspecified</pose><truncated>0</truncated><difficult>0</difficult><bndbox><xmin>899.0</xmin><ymin>495.0</ymin><xmax>1257.0</xmax><ymax>637.0</ymax></bndbox></object><object><name>car</name><pose>Unspecified</pose><truncated>0</truncated><difficult>0</difficult><bndbox><xmin>1122.0</xmin><ymin>505.0</ymin><xmax>1459.0</xmax><ymax>627.0</ymax></bndbox></object><object><name>car</name><pose>Unspecified</pose><truncated>0</truncated><difficult>0</difficult><bndbox><xmin>1333.0</xmin><ymin>509.0</ymin><xmax>1596.0</xmax><ymax>626.0</ymax></bndbox></object></annotations>